myao/__init__.py
myao/containers.py
myao/errors.py
myao/extractors.py
myao/magnets.py
myao/parameters.py
myao/sites.py
myao/urls.py
myao/utils.py
myao-0.0.2.dist-info/LICENSE
myao-0.0.2.dist-info/METADATA
myao-0.0.2.dist-info/WHEEL
myao-0.0.2.dist-info/RECORD
