Metadata-Version: 2.1
Name: myao
Version: 0.0.2
Summary: A flexible Nyaa API written in Python
Home-page: https://pypi.org/project/myao/
License: MIT
Keywords: nyaa,nyaa-api,nyaa-rss,nyaasi,nyaa-si,sukebei,sukebei-api,sukebei-rss,nyaa.land,nyaa-land,nyaa.land-api,nyaa-land-api,torrent,torrent download,torrent-api,python-api
Author: Simone Gentili
Author-email: gensydev@gmail.com
Requires-Python: >=3.6,<4.0
Classifier: License :: OSI Approved :: MIT License
Classifier: Programming Language :: Python :: 3
Classifier: Programming Language :: Python :: 3.6
Classifier: Programming Language :: Python :: 3.7
Classifier: Programming Language :: Python :: 3.8
Classifier: Programming Language :: Python :: 3.9
Classifier: Programming Language :: Python :: 3.10
Classifier: Programming Language :: Python :: 3.11
Classifier: Programming Language :: Python :: 3.12
Requires-Dist: beautifulsoup4 (>=4.8.0,<5.0.0)
Project-URL: Repository, https://github.com/g3nsy/myao
